tesla/__init__.py
tesla/auth/__init__.py
tesla/auth/decorators.py
tesla/auth/forms.py
tesla/auth/modal.py
tesla/auth/views.py
tesla/context/__init__.py
tesla/database/__init__.py
tesla/database/jsondb/__init__.py
tesla/database/jsondb/schema.py
tesla/database/localdb/__init__.py
tesla/exceptions/__init__.py
tesla/form/__init__.py
tesla/functions/__init__.py
tesla/media/__init__.py
tesla/messages/__init__.py
tesla/middleware/__init__.py
tesla/middleware/auth.py
tesla/modal/__init__.py
tesla/pyhtml/__init__.py
tesla/pyhtml/formater.py
tesla/pyhtml/js.py
tesla/pyhtml/server.py
tesla/pyhtml/tags.py
tesla/pyhtml/watcher.py
tesla/request/__init__.py
tesla/response/__init__.py
tesla/router/__init__.py
tesla/router/url.py
tesla/session/__init__.py
tesla/static/__init__.py
tesla/template/__init__.py
web_tesla-0.0.6.dist-info/METADATA
web_tesla-0.0.6.dist-info/WHEEL
web_tesla-0.0.6.dist-info/top_level.txt
web_tesla-0.0.6.dist-info/RECORD
