Metadata-Version: 2.1
Name: web-tesla
Version: 0.0.6
Summary: A flexiable web framework
Home-page: UNKNOWN
Author: Jafar idris
Author-email: <mail@neuralnine.com>
License: UNKNOWN
Keywords: python,web,auth
Platform: UNKNOWN
Classifier: Development Status :: 1 - Planning
Classifier: Intended Audience :: Developers
Classifier: Programming Language :: Python :: 3
Classifier: Operating System :: Unix
Classifier: Operating System :: MacOS :: MacOS X
Classifier: Operating System :: Microsoft :: Windows
Requires-Dist: uuid
Requires-Dist: jinja2
